describe/__init__.py
describe/apps.py
describe/encoders.py
describe/management/__init__.py
describe/management/commands/__init__.py
describe/management/commands/describe.py
describe/utils.py
django_describe-0.0.1.dist-info/licenses/LICENSE
django_describe-0.0.1.dist-info/WHEEL
django_describe-0.0.1.dist-info/METADATA
django_describe-0.0.1.dist-info/RECORD
