Metadata-Version: 2.4
Name: django-describe
Version: 0.0.1
Summary: Generate reports containing information on the runtime configuration of a Django site, after everything has been loaded or created and initialised.
Keywords: Django,metadata
Author: Stuart MacKay
Author-email: Stuart MacKay <smackay@fastmail.com>
License-Expression: MIT
License-File: LICENSE
Classifier: Development Status :: 1 - Planning
Classifier: Intended Audience :: Developers
Classifier: Framework :: Django
Classifier: Framework :: Django :: 5.2
Classifier: Framework :: Django :: 6
Classifier: Natural Language :: English
Classifier: Programming Language :: Python :: 3.12
Classifier: Programming Language :: Python :: 3.13
Classifier: Programming Language :: Python :: 3.14
Requires-Dist: django>=5.2
Requires-Python: >=3.12
